[
  {
    "pos_tag": "NNG"
  },
  {
    "pos_tag": "NNP"
  },
  {
    "pos_tag": "NNB"
  },
  {
    "pos_tag": "NP"
  },
  {
    "pos_tag": "NR"
  },
  {
    "pos_tag": "VV"
  },
  {
    "pos_tag": "VA"
  },
  {
    "pos_tag": "VX"
  },
  {
    "pos_tag": "VCP"
  },
  {
    "pos_tag": "VCN"
  },
  {
    "pos_tag": "MMA"
  },
  {
    "pos_tag": "MMD"
  },
  {
    "pos_tag": "MMN"
  },
  {
    "pos_tag": "MAG"
  },
  {
    "pos_tag": "MAJ"
  },
  {
    "pos_tag": "IC"
  },
  {
    "pos_tag": "JKS"
  },
  {
    "pos_tag": "JKC"
  },
  {
    "pos_tag": "JKG"
  },
  {
    "pos_tag": "JKO"
  },
  {
    "pos_tag": "JKB"
  },
  {
    "pos_tag": "JKV"
  },
  {
    "pos_tag": "JKQ"
  },
  {
    "pos_tag": "JX"
  },
  {
    "pos_tag": "JC"
  },
  {
    "pos_tag": "EP"
  },
  {
    "pos_tag": "EF"
  },
  {
    "pos_tag": "EC"
  },
  {
    "pos_tag": "ETN"
  },
  {
    "pos_tag": "ETM"
  },
  {
    "pos_tag": "XPN"
  },
  {
    "pos_tag": "XSN"
  },
  {
    "pos_tag": "XSV"
  },
  {
    "pos_tag": "XSA"
  },
  {
    "pos_tag": "XR"
  },
  {
    "pos_tag": "SF"
  },
  {
    "pos_tag": "SP"
  },
  {
    "pos_tag": "SS"
  },
  {
    "pos_tag": "SE"
  },
  {
    "pos_tag": "SO"
  },
  {
    "pos_tag": "SL"
  },
  {
    "pos_tag": "SH"
  },
  {
    "pos_tag": "SN"
  },
  {
    "pos_tag": "SW"
  },
  {
    "pos_tag": "NF"
  },
  {
    "pos_tag": "NB"
  },
  {
    "pos_tag": "SN"
  },
  {
    "pos_tag": "NV"
  },
  {
    "pos_tag": "NA"
  }
]